ngramratio/__init__.py
ngramratio/ngramratio.py
ngramratio-1.0.0.dist-info/LICENSE
ngramratio-1.0.0.dist-info/METADATA
ngramratio-1.0.0.dist-info/WHEEL
ngramratio-1.0.0.dist-info/top_level.txt
ngramratio-1.0.0.dist-info/RECORD
