Metadata-Version: 2.1
Name: ngramratio
Version: 1.0.0
Summary: N-grams based similarity score
Home-page: https://github.com/gi-ba-bu/python-n-gram-ratio
Author: Giacomo Baldo
Author-email: baldogiacomophd@gmail.com
Project-URL: Bug Tracker, https://github.com/gi-ba-bu/python-n-gram-ratio/issues
Classifier: Programming Language :: Python :: 3
Classifier: License :: OSI Approved :: MIT License
Classifier: Operating System :: OS Independent
Classifier: Topic :: Software Development :: Libraries
Requires-Python: >=3.6
License-File: LICENSE
